lecroydso/__about__.py
lecroydso/__init__.py
lecroydso/activedso.py
lecroydso/dsoconnection.py
lecroydso/enums.py
lecroydso/errors.py
lecroydso/lecroydso.py
lecroydso/lecroyvisa.py
LeCroyDSO-0.4.dist-info/AUTHORS
LeCroyDSO-0.4.dist-info/LICENSE
LeCroyDSO-0.4.dist-info/METADATA
LeCroyDSO-0.4.dist-info/WHEEL
LeCroyDSO-0.4.dist-info/top_level.txt
LeCroyDSO-0.4.dist-info/RECORD
