Metadata-Version: 2.1
Name: LeCroyDSO
Version: 0.4
Summary: Python communication utilities for LeCroy oscilloscopes
Home-page: https://github.com/lecroydso/lecroydso
Author: Ashok Bruno
Author-email: ashok.bruno@teledyne.com
Maintainer: Ashok Bruno
Maintainer-email: ashok.bruno@teledyne.com
License: MIT License
Keywords: ActiveDSO,VISA,GPIB,USBTMC,serial,RS232,measurement,acquisition
Platform: Linux
Platform: Windows
Platform: Mac
Classifier: Development Status :: 4 - Beta
Classifier: Intended Audience :: Developers
Classifier: Intended Audience :: Science/Research
Classifier: License :: OSI Approved :: MIT License
Classifier: Operating System :: Microsoft :: Windows
Classifier: Operating System :: POSIX :: Linux
Classifier: Operating System :: MacOS :: MacOS X
Classifier: Programming Language :: Python
Classifier: Topic :: Scientific/Engineering :: Interface Engine/Protocol Translator
Classifier: Topic :: Software Development :: Libraries :: Python Modules
Classifier: Programming Language :: Python :: 3
Classifier: Programming Language :: Python :: 3.6
Classifier: Programming Language :: Python :: 3.7
Classifier: Programming Language :: Python :: 3.8
Classifier: Programming Language :: Python :: 3.9
Requires-Python: >=3.6
Requires-Dist: numpy
Requires-Dist: pyvisa
Requires-Dist: pywin32
Requires-Dist: typing-extensions
Requires-Dist: dataclasses ; python_version < "3.7"
Requires-Dist: importlib-metadata ; python_version < "3.8"
